{
  "id": "manual_20250601_035004",
  "url": "https://archive.is/5v9Md#selection-279.0-283.44",
  "title": "Column / Behind the Curtain Behind the Curtain: A white-collar bloodbath",
  "content": "Manual URL entry.",
  "source_type": "manual_url",
  "collected_at": "2025-06-01 03:50:04.973479",
  "raw_metadata": "{\"entry_method\": \"manual_url\", \"category\": \"general\", \"notes\": \"\", \"added_by\": \"manual_interface\", \"ai_impact_category\": \"augment\", \"processed_at\": \"2025-06-01T14:31:08.266883\", \"processing_method\": \"automated_keyword\"}"
}